VerdictFormat/VerdictFormat.py
VerdictFormat/__init__.py
VerdictFormat-1.6.dist-info/LICENSE.txt
VerdictFormat-1.6.dist-info/METADATA
VerdictFormat-1.6.dist-info/WHEEL
VerdictFormat-1.6.dist-info/top_level.txt
VerdictFormat-1.6.dist-info/RECORD
