Metadata-Version: 2.1
Name: VerdictFormat
Version: 1.6
Summary: To format verdict
Home-page: https://github.com/Josiriser/VerdictFormat
Author: Josiriser
Author-email: josiriser@gmail.com
License: UNKNOWN
Platform: UNKNOWN
Classifier: Programming Language :: Python :: 3
Classifier: License :: OSI Approved :: MIT License
Classifier: Operating System :: OS Independent
Requires-Python: >=3.6
